{"cameraMode":{"drawMode":0,"name":"Shaded","section":"Shading Mode"},"sceneLighting":false,"audioPlay":false,"sceneViewState":{"m_AlwaysRefresh":false,"showFog":true,"showSkybox":false,"showFlares":true,"showImageEffects":true,"showParticleSystems":true,"showVisualEffectGraphs":true,"m_FxEnabled":true},"in2DMode":false,"pivot":{"x":-0.5341734886169434,"y":0.09308505058288574,"z":-1.3801244497299195},"rotation":{"x":-0.13663765788078309,"y":0.5962828397750855,"z":-0.10388918966054917,"w":-0.7842195630073547},"size":2.0109364986419679,"orthographic":false}